wise_api_client/__init__.py
wise_api_client/api_client.py
wise_api_client/api_response.py
wise_api_client/configuration.py
wise_api_client/exceptions.py
wise_api_client/py.typed
wise_api_client/rest.py
wise_api_client/api/__init__.py
wise_api_client/api/activities_api.py
wise_api_client/api/profiles_api.py
wise_api_client/api/quotes_api.py
wise_api_client/api/recipients_api.py
wise_api_client/api/transfers_api.py
wise_api_client/models/__init__.py
wise_api_client/models/account_requirements_inner.py
wise_api_client/models/account_requirements_inner_fields_inner.py
wise_api_client/models/account_requirements_inner_fields_inner_group_inner.py
wise_api_client/models/account_requirements_inner_fields_inner_group_inner_values_allowed_inner.py
wise_api_client/models/activities_response.py
wise_api_client/models/activity.py
wise_api_client/models/activity_resource.py
wise_api_client/models/address.py
wise_api_client/models/amount.py
wise_api_client/models/api_error.py
wise_api_client/models/banking_partner_invoice.py
wise_api_client/models/business_profile.py
wise_api_client/models/client_error.py
wise_api_client/models/client_error_detail.py
wise_api_client/models/create_authenticated_quote_request.py
wise_api_client/models/create_authenticated_quote_request_base.py
wise_api_client/models/create_authenticated_source_amount_quote_request.py
wise_api_client/models/create_authenticated_target_amount_quote_request.py
wise_api_client/models/create_business_profile_request.py
wise_api_client/models/create_partner_licence_transfer_request.py
wise_api_client/models/create_personal_profile_request.py
wise_api_client/models/create_personal_profile_request_address.py
wise_api_client/models/create_personal_profile_request_contact_details.py
wise_api_client/models/create_recipient_request.py
wise_api_client/models/create_standard_transfer_request.py
wise_api_client/models/create_third_party_transfer_request.py
wise_api_client/models/create_unauthenticated_quote_request.py
wise_api_client-0.6.0.dist-info/licenses/LICENSE
wise_api_client-0.6.0.dist-info/METADATA
wise_api_client-0.6.0.dist-info/WHEEL
wise_api_client-0.6.0.dist-info/top_level.txt
wise_api_client-0.6.0.dist-info/RECORD
