Metadata-Version: 2.4
Name: wise-api-client
Version: 0.6.0
Summary: (TransferWise) Wise Platform API
Home-page: 
Author: Max Ploter
Author-email: maksim.ploter@gmail.com
License: MIT
Keywords: OpenAPI,OpenAPI-Generator,(TransferWise) Wise Platform API
License-File: LICENSE
Requires-Dist: urllib3<3.0.0,>=2.1.0
Requires-Dist: python-dateutil>=2.8.2
Requires-Dist: pydantic>=2
Requires-Dist: typing-extensions>=4.7.1
Dynamic: author
Dynamic: author-email
Dynamic: description
Dynamic: description-content-type
Dynamic: keywords
Dynamic: license
Dynamic: license-file
Dynamic: requires-dist
Dynamic: summary
